{
  "topology": {
    "node0": {
      "network": {
        "node1": {
          "latency": "500"
        },
        "node2": {
          "latency": "200"
        }
      }
    },
    "node1": {
      "network": {
        "node2": {
          "latency": "300"
        }
      }
    }
  },
  "data": {
    "data0": {
      "sendRate": "3",
      "location": "node1"
    },
    "data1": {
      "sendRate": "1",
      "location": "node2"
    },
    "data2": {
      "sendRate": "1",
      "location": "node3"
    }
  },
  "system": {
    "worker0": {
      "ram": "1Gi",
      "cpu": "1",
      "replicas": 2,
      "location": "node1",
      "modelDepth": "101"
    },
    "worker1": {
      "ram": "1Gi",
      "cpu": "1",
      "replicas": 1,
      "location": "node2",
      "modelDepth": "50"
    }
  }
}